itk/IOOpenJPHPython.py
itk/itkOpenJPHImageIOPython.py
itk/_IOOpenJPHPython.abi3.so
itk/Configuration/IOOpenJPHConfig.py
itk/Configuration/IOOpenJPH_snake_case.py
itk_ioopenjph-1.3.0.dist-info/entry_points.txt
itk_ioopenjph-1.3.0.dist-info/WHEEL
itk_ioopenjph-1.3.0.dist-info/RECORD
itk_ioopenjph-1.3.0.dist-info/METADATA
itk_ioopenjph-1.3.0.dist-info/licenses/LICENSE
itk_ioopenjph.libs/libtbb-f489fd38.so.12.9
